__init__.py
run_tests.py
lily_unit_test/__init__.py
lily_unit_test/classification.py
lily_unit_test/html_report.py
lily_unit_test/logger.py
lily_unit_test/test_runner.py
lily_unit_test/test_settings.py
lily_unit_test/test_suite.py
lily_unit_test/artifacts/html_report_template.html
test_suites/__init__.py
test_suites/test_environment_cleanup.py
test_suites/test_environment_setup.py
test_suites/basic_pass_fail/__init__.py
test_suites/basic_pass_fail/test_empty.py
test_suites/basic_pass_fail/test_fail_no_exception.py
test_suites/basic_pass_fail/test_fail_with_exception.py
test_suites/basic_pass_fail/test_order.py
test_suites/basic_pass_fail/test_pass.py
test_suites/basic_pass_fail/test_setup_fail_exception.py
test_suites/basic_pass_fail/test_setup_fail_return_false.py
test_suites/basic_pass_fail/test_teardown_fail_exception.py
test_suites/specific_functions/__init__.py
test_suites/specific_functions/test_failing_thread.py
test_suites/specific_functions/test_threading.py
test_suites/specific_functions/test_wait_for.py
test_suites/test_fail_methods/__init__.py
test_suites/test_fail_methods/test_fail_if_no_exception.py
test_suites/test_fail_methods/test_fail_if_with_exception.py
test_suites/test_fail_methods/test_fail_no_exception.py
test_suites/test_fail_methods/test_fail_with_exception.py
lily_unit_test-1.10.0.dist-info/METADATA
lily_unit_test-1.10.0.dist-info/WHEEL
lily_unit_test-1.10.0.dist-info/license.txt
lily_unit_test-1.10.0.dist-info/top_level.txt
lily_unit_test-1.10.0.dist-info/RECORD
