Metadata-Version: 2.1
Name: lily-unit-test
Version: 1.10.0
Summary: Python Unit Test package by LilyTronics
Author-email: LilyTronics <info@lilytronics.nl>
Project-URL: Homepage, https://github.com/LilyTronics/lily-py-unit-test
Project-URL: Issues, https://github.com/LilyTronics/lily-py-unit-test/issues
Classifier: Programming Language :: Python :: 3
Classifier: Operating System :: OS Independent
Classifier: Development Status :: 5 - Production/Stable
Requires-Python: >=3.10
License-File: license.txt
